dan_airflow_plugins/__init__.py
dan_airflow_plugins/plugin.py
dan_airflow_plugins/operators/__init__.py
dan_airflow_plugins/operators/dan_operator.py
dan_airflow_plugins-0.1.0.dist-info/METADATA
dan_airflow_plugins-0.1.0.dist-info/WHEEL
dan_airflow_plugins-0.1.0.dist-info/entry_points.txt
dan_airflow_plugins-0.1.0.dist-info/top_level.txt
dan_airflow_plugins-0.1.0.dist-info/RECORD
