Metadata-Version: 2.1
Name: dan-airflow-plugins
Version: 0.1.0
Summary: Apache Airflow Operator
Home-page: https://github.com/dconger/airflow-plugins-example
Author: Dan Conger
Author-email: dconger2@gmail.com
License: Apache License, Version 2.0
Platform: UNKNOWN
Classifier: Operating System :: OS Independent
Classifier: Programming Language :: Python
Classifier: Topic :: Software Development :: Libraries :: Python Modules
Classifier: Programming Language :: Python :: 3
Classifier: Programming Language :: Python :: 3.3
Classifier: Programming Language :: Python :: 3.4
Classifier: Programming Language :: Python :: 3.5
Classifier: Programming Language :: Python :: 3.6
Classifier: Programming Language :: Python :: 3.7
Classifier: Programming Language :: Python :: 3.8
Requires-Dist: apache-airflow
